bpi_13_experimental_frontend/__init__.py
bpi_13_experimental_frontend/run_model.py
domain_model/__init__.py
domain_model/bpi13_actors.py
domain_model/bpi13_model.py
domain_model/utils.py
bpi_13_python-0.1a4.dist-info/LICENSE
bpi_13_python-0.1a4.dist-info/METADATA
bpi_13_python-0.1a4.dist-info/WHEEL
bpi_13_python-0.1a4.dist-info/top_level.txt
bpi_13_python-0.1a4.dist-info/RECORD
