Metadata-Version: 2.1
Name: bpi-13-python
Version: 0.1a4
Summary: A model of the BPI '13 process mining challenge.
Home-page: http://probablytom.com/
Author: Tom Wallis
Author-email: w.wallis.1@research.gla.ac.uk
License: MIT
Platform: UNKNOWN
Classifier: License :: OSI Approved :: MIT License
Classifier: Programming Language :: Python
Classifier: Programming Language :: Python :: 2
Classifier: Programming Language :: Python :: 2.7
Classifier: Programming Language :: Python :: Implementation :: CPython
Classifier: Programming Language :: Python :: Implementation :: PyPy
Requires-Python: <3
Requires-Dist: drawer
Requires-Dist: theatre-au
Requires-Dist: actor-au
Requires-Dist: pydysofu
Requires-Dist: xes
